LICENSE
MANIFEST.in
README.md
setup.cfg
setup.py
netdoc/__init__.py
netdoc/dictionaries.py
netdoc/filtersets.py
netdoc/forms.py
netdoc/models.py
netdoc/navigation.py
netdoc/nornir_inventory.py
netdoc/search.py
netdoc/signals.py
netdoc/tables.py
netdoc/tasks.py
netdoc/topologies.py
netdoc/urls.py
netdoc/utils.py
netdoc/views.py
netdoc.egg-info/PKG-INFO
netdoc.egg-info/SOURCES.txt
netdoc.egg-info/dependency_links.txt
netdoc.egg-info/not-zip-safe
netdoc.egg-info/requires.txt
netdoc.egg-info/top_level.txt
netdoc/api/__init__.py
netdoc/api/serializers.py
netdoc/api/urls.py
netdoc/api/views.py
netdoc/discoverers/__init__.py
netdoc/discoverers/json_vmware_vsphere.py
netdoc/discoverers/netmiko_allied_telesis_awplus.py
netdoc/discoverers/netmiko_aruba_oscx.py
netdoc/discoverers/netmiko_cisco_ios.py
netdoc/discoverers/netmiko_cisco_ios_telnet.py
netdoc/discoverers/netmiko_cisco_nxos.py
netdoc/discoverers/netmiko_cisco_xr.py
netdoc/discoverers/netmiko_hp_comware.py
netdoc/discoverers/netmiko_hp_procurve.py
netdoc/discoverers/netmiko_hp_procurve_telnet.py
netdoc/discoverers/netmiko_huawei_vrp.py
netdoc/discoverers/netmiko_linux.py
netdoc/discoverers/xml_panw_ngfw.py
netdoc/ingestors/__init__.py
netdoc/ingestors/json_vmware_vsphere_pyvmomi.py
netdoc/ingestors/netmiko_allied_telesis_awplus_hostname.py
netdoc/ingestors/netmiko_allied_telesis_awplus_show_arp.py
netdoc/ingestors/netmiko_allied_telesis_awplus_show_etherchannel_summary.py
netdoc/ingestors/netmiko_allied_telesis_awplus_show_interface.py
netdoc/ingestors/netmiko_allied_telesis_awplus_show_interface_switchport.py
netdoc/ingestors/netmiko_allied_telesis_awplus_show_ip_route.py
netdoc/ingestors/netmiko_allied_telesis_awplus_show_lldp_neighbors_detail.py
netdoc/ingestors/netmiko_allied_telesis_awplus_show_mac_address_table.py
netdoc/ingestors/netmiko_allied_telesis_awplus_show_static_channel_group.py
netdoc/ingestors/netmiko_allied_telesis_awplus_show_system.py
netdoc/ingestors/netmiko_allied_telesis_awplus_show_vlan_all.py
netdoc/ingestors/netmiko_aruba_aoscx_hostname.py
netdoc/ingestors/netmiko_aruba_aoscx_show_arp_all_vrfs.py
netdoc/ingestors/netmiko_aruba_aoscx_show_interface.py
