Metadata-Version: 2.1
Name: netdoc
Version: 3.5.22
Summary: Automatic Network Documentation plugin for NetBox
Home-page: https://github.com/dainok/netdoc
Author: Andrea Dainese
Author-email: andrea@adainese.it
License: GNU v3.0
Project-URL: Source, https://github.com/dainok/netdoc
Classifier: Programming Language :: Python
Classifier: Programming Language :: Python :: 3
Classifier: Programming Language :: Python :: 3 :: Only
License-File: LICENSE
